fasterui/__init__.py
fasterui/__main__.py
fasterui/__version__.py
fasterui/components.py
fasterui/examples/__init__.py
fasterui/examples/button.py
fasterui/examples/page.py
fasterui-0.1.13.dist-info/METADATA
fasterui-0.1.13.dist-info/WHEEL
fasterui-0.1.13.dist-info/entry_points.txt
fasterui-0.1.13.dist-info/top_level.txt
fasterui-0.1.13.dist-info/RECORD
